README.md
setup.py
tests/test_gym_pusht.py
tests/test_keys.py
tests/test_pi0.py
tests/test_pi0fast.py
tests/test_safetensor.py
tests/test_smolvla.py
vlaholo/__init__.py
vlaholo/constants.py
vlaholo/params.py
vlaholo.egg-info/PKG-INFO
vlaholo.egg-info/SOURCES.txt
vlaholo.egg-info/dependency_links.txt
vlaholo.egg-info/requires.txt
vlaholo.egg-info/top_level.txt
vlaholo/common/__init__.py
vlaholo/common/defaults.py
vlaholo/common/envs_config.py
vlaholo/common/eval_config.py
vlaholo/common/optimizers_config.py
vlaholo/common/parser.py
vlaholo/common/policies_config.py
vlaholo/common/schedulers_config.py
vlaholo/common/train_config.py
vlaholo/datasets/__init__.py
vlaholo/datasets/build_dataset.py
vlaholo/datasets/compute_stats.py
vlaholo/datasets/image_writer.py
vlaholo/datasets/lerobot_dataset.py
vlaholo/datasets/sampler.py
vlaholo/datasets/transforms.py
vlaholo/datasets/video_utils.py
vlaholo/infer/__init__.py
vlaholo/infer/eval_env.py
vlaholo/models/__init__.py
vlaholo/models/build_model.py
vlaholo/models/normalize.py
vlaholo/models/pretrained.py
vlaholo/models/pi0/__init__.py
vlaholo/models/pi0/configuration_pi0.py
vlaholo/models/pi0/flex_attention.py
vlaholo/models/pi0/modeling_pi0.py
vlaholo/models/pi0/paligemma_with_expert.py
vlaholo/models/pi0_5/__init__.py
vlaholo/models/pi0fast/__init__.py
vlaholo/models/pi0fast/configuration_pi0fast.py
vlaholo/models/pi0fast/modeling_pi0fast.py
vlaholo/models/smolvla/__init__.py
vlaholo/models/smolvla/configuration_smolvla.py
vlaholo/models/smolvla/modeling_smolvla.py
vlaholo/models/smolvla/smolvlm_with_expert.py
vlaholo/utils/__init__.py
vlaholo/utils/dataset_utils.py
vlaholo/utils/hub.py
vlaholo/utils/io_utils.py
vlaholo/utils/logging_utils.py
vlaholo/utils/policies_utils.py
vlaholo/utils/random_utils.py
vlaholo/utils/train_utils.py
vlaholo/utils/utils.py